Metadata-Version: 2.1
Name: cpg-gnomad
Version: 0.6.3
Summary: Hail utilities for the Genome Aggregation Database
Home-page: https://github.com/broadinstitute/gnomad_methods
Author: The Genome Aggregation Database
Author-email: gnomad@broadinstitute.org
Project-URL: Documentation, https://broadinstitute.github.io/gnomad_methods/
Project-URL: Source Code, https://github.com/broadinstitute/gnomad_methods
Project-URL: Issues, https://github.com/broadinstitute/gnomad_methods/issues
Project-URL: Change Log, https://github.com/broadinstitute/gnomad_methods/releases
Classifier: Topic :: Scientific/Engineering :: Bio-Informatics
Classifier: Intended Audience :: Science/Research
Classifier: License :: OSI Approved :: MIT License
Classifier: Programming Language :: Python :: 3
Classifier: Development Status :: 4 - Beta
Requires-Python: >=3.6
License-File: LICENSE
Requires-Dist: hdbscan
Requires-Dist: ipywidgets
Requires-Dist: scikit-learn
Requires-Dist: slackclient (==2.5.0)
